pymaxmusic/__init__.py
pymaxmusic/pymax.py
pymaxmusic-0.0.5.dist-info/METADATA
pymaxmusic-0.0.5.dist-info/WHEEL
pymaxmusic-0.0.5.dist-info/licenses/LICENSE.txt
pymaxmusic-0.0.5.dist-info/RECORD
